endfield_daily/__init__.py
endfield_daily/_version.py
endfield_daily/api.py
endfield_daily/cli.py
endfield_daily/config.py
endfield_daily/notifications.py
endfield_daily/scheduler.py
endfield_daily_helper-1.0.5.dist-info/METADATA
endfield_daily_helper-1.0.5.dist-info/WHEEL
endfield_daily_helper-1.0.5.dist-info/entry_points.txt
endfield_daily_helper-1.0.5.dist-info/RECORD
