Metadata-Version: 2.4
Name: endfield-daily-helper
Version: 1.0.5
Summary: Automatically claim daily login rewards for Arknights: Endfield
Project-URL: Homepage, https://github.com/Chiraitori/endfield-daily-helper
Project-URL: Repository, https://github.com/Chiraitori/endfield-daily-helper
Project-URL: Issues, https://github.com/Chiraitori/endfield-daily-helper/issues
Author: Chiraitori
License-Expression: MIT
Keywords: arknights,daily-login,endfield,gacha,gryphline,hypergryph,skport
Classifier: Development Status :: 4 - Beta
Classifier: Environment :: Console
Classifier: Intended Audience :: End Users/Desktop
Classifier: License :: OSI Approved :: MIT License
Classifier: Operating System :: OS Independent
Classifier: Programming Language :: Python :: 3
Classifier: Programming Language :: Python :: 3.9
Classifier: Programming Language :: Python :: 3.10
Classifier: Programming Language :: Python :: 3.11
Classifier: Programming Language :: Python :: 3.12
Classifier: Topic :: Games/Entertainment
Classifier: Topic :: Utilities
Requires-Python: >=3.9
Requires-Dist: pytz>=2023.3
Requires-Dist: requests>=2.28.0
Requires-Dist: schedule>=1.2.0
Requires-Dist: tomli>=2.0.0; python_version < '3.11'
Provides-Extra: dev
Requires-Dist: black; extra == 'dev'
Requires-Dist: build; extra == 'dev'
Requires-Dist: pytest; extra == 'dev'
Requires-Dist: ruff; extra == 'dev'
Requires-Dist: twine; extra == 'dev'
